{
	"data": [
		{
			"path": "518",
			"title": "개발",
			"detail": [
				{
					"path": "",
					"title": "개발 전체"
				},
				{
					"path": "10110",
					"title": "소프트웨어 엔지니어"
				},
				{
					"path": "873",
					"title": "웹 개발자"
				},
				{
					"path": "872",
					"title": "서버 개발자"
				},
				{
					"path": "669",
					"title": "프론트엔드 개발자"
				},
				{
					"path": "660",
					"title": "자바 개발자"
				},
				{
					"path": "900",
					"title": "C,C++ 개발자"
				},
				{
					"path": "899",
					"title": "파이썬 개발자"
				},
				{
					"path": "1634",
					"title": "Node.js 개발자"
				},
				{
					"path": "895",
					"title": "머신러능 엔지니어"
				},
				{
					"path": "655",
					"title": "데이터 엔지니어"
				},
				{
					"path": "677",
					"title": "안드로이드 개발자"
				},
				{
					"path": "674",
					"title": "DevOps / 시스템 관리자"
				},
				{
					"path": "665",
					"title": "시스템, 네트워크 관리자"
				},
				{
					"path": "678",
					"title": "iOS 개발자"
				},
				{
					"path": "877",
					"title": "개발 매니저"
				},
				{
					"path": "1024",
					"title": "데이터 사이언티스트"
				},
				{
					"path": "1026",
					"title": "기술지원"
				},
				{
					"path": "676",
					"title": "QA, 테스트 엔지니어"
				},
				{
					"path": "658",
					"title": "임베디드 개발자"
				},
				{
					"path": "671",
					"title": "보안 엔지니어"
				},
				{
					"path": "1025",
					"title": "빅데이터 엔지니어"
				},
				{
					"path": "672",
					"title": "하드웨어 엔지니어"
				},
				{
					"path": "876",
					"title": "프로덕트 매니저"
				},
				{
					"path": "10111",
					"title": "크로스플랫폼 앱 개발자"
				},
				{
					"path": "1027",
					"title": "블록체인 플랫폼 엔지니어"
				},
				{
					"path": "10231",
					"title": "DBA"
				},
				{
					"path": "661",
					"title": "웹 퍼블리셔"
				},
				{
					"path": "893",
					"title": "PHP 개발자"
				},
				{
					"path": "896",
					"title": "ERP전문가"
				},
				{
					"path": "939",
					"title": ".NET 개발자"
				},
				{
					"path": "10230",
					"title": "영상, 음성 엔지니어"
				},
				{
					"path": "898",
					"title": "그래픽스 엔지니어"
				},
				{
					"path": "795",
					"title": "CTO, Chief Technology Officer"
				},
				{
					"path": "1022",
					"title": "VR 엔지니어"
				},
				{
					"path": "10112",
					"title": "BI 엔지니어"
				},
				{
					"path": "894",
					"title": "루비온레일즈 개발자"
				},
				{
					"path": "793",
					"title": "CIO, Chief Information Officer"
				}
			]
		},
		{
			"path": "507",
			"title": "경영·비즈니스"
		},
		{
			"path": "523",
			"title": "마케팅·광고"
		},
		{
			"path": "511",
			"title": "디자인"
		},
		{
			"path": "530",
			"title": "영업"
		},
		{
			"path": "510",
			"title": "고객서비스·리테일"
		},
		{
			"path": "524",
			"title": "미디어"
		},
		{
			"path": "513",
			"title": "엔지니어링·설계"
		},
		{
			"path": "959",
			"title": "게임 제작"
		},
		{
			"path": "517",
			"title": "HR"
		},
		{
			"path": "508",
			"title": "금융"
		},
		{
			"path": "522",
			"title": "제조·생산"
		},
		{
			"path": "532",
			"title": "물류·무역"
		},
		{
			"path": "10101",
			"title": "교육"
		},
		{
			"path": "515",
			"title": "의료·제약·바이오"
		},
		{
			"path": "521",
			"title": "법률·법집행기관"
		},
		{
			"path": "509",
			"title": "건설·시설"
		},
		{
			"path": "10057",
			"title": "식·음료"
		},
		{
			"path": "514",
			"title": "공공·복지"
		}
	]
}
